{
  "tables": [
    {
      "name": "users",
      "columns": [
        {
          "name": "id",
          "data_type": {
            "Int": 10
          },
          "is_primary": true,
          "not_null": true
        },
        {
          "name": "name",
          "data_type": {
            "Varchar": 255
          },
          "is_primary": false,
          "not_null": true
        },
        {
          "name": "email",
          "data_type": {
            "Varchar": 255
          },
          "is_primary": false,
          "not_null": false
        }
      ],
      "data": [
        [
          "1",
          "'''Alice Smith'''",
          "alice@example.com"
        ],
        [
          "2",
          "Bob",
          "bob@example.com"
        ]
      ]
    },
    {
      "name": "users",
      "columns": [
        {
          "name": "user_id",
          "data_type": {
            "Int": 10
          },
          "is_primary": true,
          "not_null": false
        },
        {
          "name": "username",
          "data_type": {
            "Varchar": 50
          },
          "is_primary": false,
          "not_null": false
        },
        {
          "name": "password",
          "data_type": {
            "Varchar": 100
          },
          "is_primary": false,
          "not_null": false
        }
      ],
      "data": []
    },
    {
      "name": "students",
      "columns": [
        {
          "name": "id",
          "data_type": {
            "Int": 10
          },
          "is_primary": true,
          "not_null": false
        },
        {
          "name": "name",
          "data_type": {
            "Varchar": 255
          },
          "is_primary": false,
          "not_null": false
        },
        {
          "name": "email",
          "data_type": {
            "Varchar": 255
          },
          "is_primary": false,
          "not_null": false
        },
        {
          "name": "age",
          "data_type": {
            "Int": 10
          },
          "is_primary": false,
          "not_null": false
        }
      ],
      "data": [
        [
          "1",
          "'Alice'",
          "'alice@school.edu'",
          "20"
        ],
        [
          "2",
          "'Bob'",
          "'bob@school.edu'",
          "22"
        ],
        [
          "3",
          "'Charlie'",
          "NULL",
          "19"
        ]
      ]
    },
    {
      "name": "students",
      "columns": [
        {
          "name": "id",
          "data_type": {
            "Int": 10
          },
          "is_primary": false,
          "not_null": false
        },
        {
          "name": "name",
          "data_type": {
            "Varchar": 255
          },
          "is_primary": false,
          "not_null": false
        },
        {
          "name": "email",
          "data_type": {
            "Varchar": 255
          },
          "is_primary": false,
          "not_null": false
        },
        {
          "name": "age",
          "data_type": {
            "Int": 10
          },
          "is_primary": false,
          "not_null": false
        }
      ],
      "data": []
    }
  ]
}